[
  {
    "username": "Volodymyr",
    "password": "123456789"
  },
  {
    "username": "vova",
    "password": "123",
    "email": "adsd@sfsdf",
    "first_name": "asf",
    "last_name": "sf",
    "date_of_birth": "2023-10-27"
  },
  {
    "username": "vov2",
    "password": "123",
    "email": "dasd@asda",
    "first_name": "asd",
    "last_name": "asd",
    "date_of_birth": "2023-10-27"
  },
  {
    "username": "asda",
    "password": "asd",
    "email": "asda@sdas",
    "first_name": "asd",
    "last_name": "asd",
    "date_of_birth": "2023-10-27"
  },
  {
    "username": "asdasd",
    "password": "asdasd",
    "email": "asd@asdasdas",
    "first_name": "asd",
    "last_name": "asd",
    "date_of_birth": "2023-10-27"
  },
  {
    "username": "asd",
    "password": "asd",
    "email": "asd@asd",
    "first_name": "asd",
    "last_name": "asd",
    "date_of_birth": "2023-10-27"
  },
  {
    "username": "Vova1",
    "password": "123",
    "email": "qweq@qweqw",
    "first_name": "123wqe",
    "last_name": "qweqwe",
    "date_of_birth": "2023-11-02"
  },
  {
    "username": "Vova2",
    "password": "123",
    "email": "wqweq@qweqw",
    "first_name": "qwe",
    "last_name": "qweqw",
    "date_of_birth": "2023-11-02"
  },
  {
    "username": "asad",
    "password": "asd",
    "email": "asd@asd",
    "first_name": "asd",
    "last_name": "asd",
    "date_of_birth": "2023-11-02"
  },
  {
    "username": "fg",
    "password": "dfgh",
    "email": "dfg@dfg",
    "first_name": "fg",
    "last_name": "dfgh",
    "date_of_birth": "2023-11-02"
  },
  {
    "username": "asdaaasdasd",
    "password": "asd",
    "email": "asd2@asda",
    "first_name": "asdasd",
    "last_name": "asdasd",
    "date_of_birth": "2023-11-02"
  },
  {
    "username": "asdasdaaaasd",
    "password": "asdasda",
    "email": "asda@asdasd",
    "first_name": "asdasd",
    "last_name": "asdasd",
    "date_of_birth": "2023-11-02"
  },
  {
    "username": "zxczxcre",
    "password": "sdfsdf",
    "email": "sdfs@sdfsdf",
    "first_name": "sdfsdf",
    "last_name": "sdfsdf",
    "date_of_birth": "2023-11-02"
  },
  {
    "username": "Vova4",
    "password": "123",
    "email": "asdas@asda",
    "first_name": "asda",
    "last_name": "asd",
    "date_of_birth": "2023-11-03"
  },
  {
    "username": "Vov1",
    "password": "123",
    "email": "qwe@qwe",
    "first_name": "Vova",
    "last_name": "Fedorov",
    "date_of_birth": "2023-11-03"
  },
  {
    "username": "Vova2",
    "password": "123",
    "email": "qwe@qwe",
    "first_name": "123",
    "last_name": "qwe",
    "date_of_birth": "2023-11-03"
  },
  {
    "username": "Vov1",
    "password": "asd",
    "email": "asd@asd",
    "first_name": "asd@asd",
    "last_name": "asda",
    "date_of_birth": "2023-11-03"
  },
  {
    "username": "eeeewew",
    "password": "werw",
    "email": "wer@sdfs",
    "first_name": "sdf",
    "last_name": "sdf",
    "date_of_birth": "2023-11-03"
  },
  {
    "username": "Get",
    "password": "123",
    "email": "asdgj@we",
    "first_name": "12qwe",
    "last_name": "we",
    "date_of_birth": "2023-11-03"
  },
  {
    "username": "gj,j,jk,",
    "password": "bjkvhkv",
    "email": "vkvhk@fgjjygj",
    "first_name": "ghjfgj",
    "last_name": "fgjhfgj",
    "date_of_birth": "2023-11-04"
  },
  {
    "username": "sdfsf",
    "password": "sdfsdf",
    "email": "sdfsf@sdfsf",
    "first_name": "sfsdf",
    "last_name": "sdfs",
    "date_of_birth": "2023-11-04"
  },
  {
    "username": "Vvov1",
    "password": "123",
    "email": "qwe@awde",
    "first_name": "qwe",
    "last_name": "qwe",
    "date_of_birth": "2023-11-04"
  },
  {
    "username": "Vov4ik1",
    "password": "123",
    "email": "qweqw@qwe",
    "first_name": "qwe",
    "last_name": "wqeq",
    "date_of_birth": "2023-11-04"
  }
]